{"cameraMode":{"drawMode":0,"name":"Shaded","section":"Shading Mode"},"sceneLighting":true,"audioPlay":false,"sceneViewState":{"m_AlwaysRefresh":false,"showFog":true,"showSkybox":true,"showFlares":true,"showImageEffects":true,"showParticleSystems":true,"showVisualEffectGraphs":true,"m_FxEnabled":true},"in2DMode":false,"pivot":{"x":593.8906860351563,"y":716.4074096679688,"z":0.854766845703125},"rotation":{"x":-0.06418842077255249,"y":-0.12119657546281815,"z":0.007873828522861004,"w":-0.990581214427948},"size":735.3494262695313,"orthographic":false}