{"cameraMode":{"drawMode":0,"name":"Shaded","section":"Shading Mode"},"sceneLighting":true,"audioPlay":false,"sceneViewState":{"m_AlwaysRefresh":false,"showFog":true,"showSkybox":true,"showFlares":true,"showImageEffects":true,"showParticleSystems":true,"showVisualEffectGraphs":true,"m_FxEnabled":true},"in2DMode":false,"pivot":{"x":-4.968529224395752,"y":4.081280708312988,"z":0.11282658576965332},"rotation":{"x":-0.12677307426929475,"y":0.10306263715028763,"z":-0.013248796574771405,"w":-0.9864861369132996},"size":4.122185707092285,"orthographic":false}