{"cameraMode":{"drawMode":0,"name":"Shaded","section":"Shading Mode"},"sceneLighting":true,"audioPlay":false,"sceneViewState":{"m_AlwaysRefresh":false,"showFog":true,"showSkybox":true,"showFlares":true,"showImageEffects":true,"showParticleSystems":true,"showVisualEffectGraphs":true,"m_FxEnabled":true},"in2DMode":false,"pivot":{"x":7.261208534240723,"y":1.677661657333374,"z":9.521712303161621},"rotation":{"x":-0.13007572293281556,"y":0.2202434241771698,"z":-0.02965318225324154,"w":-0.9662967920303345},"size":7.617980480194092,"orthographic":false}